dynamic_subdomains/__init__.py
dynamic_subdomains/decorators.py
dynamic_subdomains/defaults.py
dynamic_subdomains/forms.py
dynamic_subdomains/middleware.py
dynamic_subdomains/models.py
dynamic_subdomains/panels.py
dynamic_subdomains/reverse.py
dynamic_subdomains/urls.py
dynamic_subdomains/utils.py
dynamic_subdomains/views.py
dynamic_subdomains/templates/subdomains/panel.html
dynamic_subdomains/templatetags/__init__.py
dynamic_subdomains/templatetags/dynamic_subdomains.py
django_dynamic_subdomains_ai-0.2.2.dist-info/COPYING
django_dynamic_subdomains_ai-0.2.2.dist-info/METADATA
django_dynamic_subdomains_ai-0.2.2.dist-info/WHEEL
django_dynamic_subdomains_ai-0.2.2.dist-info/top_level.txt
django_dynamic_subdomains_ai-0.2.2.dist-info/RECORD
