Metadata-Version: 2.1
Name: django-dynamic-subdomains-ai
Version: 0.2.2
Summary: Dynamic and static subdomain support for Django.
Home-page: https://github.com/andersinno/django-dynamic-subdomains
Author: Anders
Author-email: admin@anders.fi
License: BSD
Platform: UNKNOWN
